{
  "vellicell_강남점": {
    "fetchedAt": 1778551903113,
    "placeId": "ChIJVRn7naShfDURdfgICiBsKv4",
    "data": {
      "placeId": "ChIJVRn7naShfDURdfgICiBsKv4",
      "name": "Vellicell Clinic Gangnam | 벨리셀의원 | ベリセル クリニック | 江南皮肤科 カンナム 美容皮膚科",
      "address": "South Korea, Seoul, Seocho District, Gangnam-daero, 407 3~4층",
      "rating": 4.9,
      "rating_count": 14,
      "google_url": "https://maps.google.com/?cid=18314569719518656629&g_mp=CiVnb29nbGUubWFwcy5wbGFjZXMudjEuUGxhY2VzLkdldFBsYWNlEAIYBCAA",
      "website": "https://gangnam.vellicellclinic.com/",
      "reviews": [
        {
          "author": "Cherry Leung",
          "photo": "https://lh3.googleusercontent.com/a-/ALV-UjWv-9aiopjfP4DgJ3yj-Oqs02puqidOAG8LOcmK8fZNY3BIkucm=s128-c0x00000000-cc-rp-mo",
          "rating": 5,
          "text": "Very good experience in Seoul clinic!!☺️💗 The price was reasonable, and the staff were very friendly!",
          "language": "en",
          "relative": "2 months ago",
          "publishedAt": "2026-02-23T09:00:33.867027692Z"
        },
        {
          "author": "Adeline",
          "photo": "https://lh3.googleusercontent.com/a/ACg8ocIaWhDedh2PzQqt9Q7D0aAV6Ykt60axSaSKQhAURHJXwmWfiQ=s128-c0x00000000-cc-rp-mo",
          "rating": 5,
          "text": "This is not a factory style clinic. After the skin analysis is done, the doctor himself does the review and treatment. Doctor speaks English too!",
          "language": "en",
          "relative": "in the last week",
          "publishedAt": "2026-05-11T05:08:35.918101093Z"
        },
        {
          "author": "Qian Hong Liao",
          "photo": "https://lh3.googleusercontent.com/a-/ALV-UjXnbjhM6PCKp2qKhsy0GdvutbimQU2nsyCadivowqelr4YBR_Q=s128-c0x00000000-cc-rp-mo",
          "rating": 5,
          "text": "You get a private room and the staff will come around to do the procedures. Comfortable environment and reasonable prices",
          "language": "en",
          "relative": "in the last week",
          "publishedAt": "2026-05-07T10:27:49.713118704Z"
        },
        {
          "author": "李美惠子",
          "photo": "https://lh3.googleusercontent.com/a/ACg8ocJmfRbBWhlc0F06foXQr_rTgEZ9SHCwZXg3cSBrxH-UUMLGAg=s128-c0x00000000-cc-rp-mo",
          "rating": 5,
          "text": "I got a microneedling treatment! Overall, the service was great, and the environment was nice too. I especially liked the elevator's decor, hehehe.",
          "language": "en",
          "relative": "2 months ago",
          "publishedAt": "2026-02-23T09:00:58.318931455Z"
        },
        {
          "author": "Sora",
          "photo": "https://lh3.googleusercontent.com/a-/ALV-UjXnzFPQ0LAw4XUAiHBBa14THNue3Wb5qLPIu7mCJ7gNBCDNVVo=s128-c0x00000000-cc-rp-mo",
          "rating": 5,
          "text": "The environment is great, with private rooms offering excellent privacy. The room manager and doctors are very friendly, and there's a Chinese translator available, so language barriers aren't a problem. Prices are the same in China and Korea.",
          "language": "en",
          "relative": "2 months ago",
          "publishedAt": "2026-02-21T02:46:20.394626930Z"
        }
      ]
    },
    "source": "google"
  },
  "hershe_청담점": {
    "fetchedAt": 1778551943327,
    "placeId": "ChIJPdmWXnqkfDUR8GYrJ9gv0n8",
    "data": {
      "placeId": "ChIJPdmWXnqkfDUR8GYrJ9gv0n8",
      "name": "HERSHE Plastic Surgery & Dermatology",
      "address": "730 Samseong-ro, 청담동 Gangnam District, Seoul, South Korea",
      "rating": 4.9,
      "rating_count": 101,
      "google_url": "https://maps.google.com/?cid=9210476793342682864&g_mp=CiVnb29nbGUubWFwcy5wbGFjZXMudjEuUGxhY2VzLkdldFBsYWNlEAIYBCAA",
      "website": "https://hershebeauty.com/",
      "reviews": [
        {
          "author": "Live Fully",
          "photo": "https://lh3.googleusercontent.com/a/ACg8ocLIrHa-uazbZYfYKJb7bs_gimocsjqFR6AFmC9UuIv9IeHltQ=s128-c0x00000000-cc-rp-mo",
          "rating": 5,
          "text": "The first time i had surgery procedure with HerShe was Dec 2024 for fat grafting to balance my face feature. I am very happy with the result and look very natural.\n\nSo just recently i had few more surgeries procedure (blepharoplasty, double chin removal, cheek liposuction, and botox) with Doctor Kim and Doctor Jung\n\nJessy and Dea is very helpful and friendly. From making a booking with Doctors, translate Doctors explanation during consulation, organise pick up from airport/hotel. Make all the process very easy and breeze. They go thru step by step with the client from day 1 until i going back to my country. They always make sure that we feel comfortable.\n\nAll the HerShe clinic staff are very good, profesional and kind manners. Thank you very much.",
          "language": "en",
          "relative": "3 months ago",
          "publishedAt": "2026-01-16T11:30:58.707070966Z"
        },
        {
          "author": "Leticia Eddyanto",
          "photo": "https://lh3.googleusercontent.com/a/ACg8ocJzrAyS1-lz5NLmtLTXRwfMnxGnisdGD2EODIaU45WeTOUmsg=s128-c0x00000000-cc-rp-mo",
          "rating": 5,
          "text": "The doctors and staff were incredibly kind and professional. They supported us throughout the entire process, from our arrival in Korea until our departure, making everything smooth and stress-free. Jessy provided excellent translation assistance during every step, which made communication very easy. We are truly satisfied with both the experience and the results. Highly recommended!",
          "language": "en",
          "relative": "3 months ago",
          "publishedAt": "2026-01-14T11:18:02.662581537Z"
        },
        {
          "author": "Karoline Hilling-Smith",
          "photo": "https://lh3.googleusercontent.com/a-/ALV-UjX1XJYK3UbGJ7kx_pcfiFSbYba9ZhZDX-fuuq8115MmFVsW6A=s128-c0x00000000-cc-rp-mo",
          "rating": 5,
          "text": "I had eye surgery and several other treatments at HERSHE Soul, and I couldn't be happier with my experience.\nI want to give special recognition to Jess, the international coordinator. She was absolutely wonderful throughout my entire journey. She promptly answered all my questions and provided invaluable assistance—which is so important when you're traveling to Seoul from overseas. Jess helped arrange my hotel accommodations and organized all my transportation, including airport transfers and trips to and from the clinic. Her support made everything so much easier.\nThe doctors at HERSHE are true experts in their field. They took the time to carefully listen to my needs and concerns, which gave me great confidence in their care. I felt I was in excellent hands throughout the entire process.\nAfter my procedure, I was pleasantly surprised to receive a generous care package filled with fresh fruits, vegetables, drinks, and delicious pumpkin soup. These thoughtful touches really demonstrated how much they care about their patients' recovery.\nI highly recommend HERSHE Soul to anyone considering cosmetic procedures in Korea. The combination of skilled doctors, exceptional international patient support, and genuine care makes this clinic stand out.",
          "language": "en",
          "relative": "5 months ago",
          "publishedAt": "2025-11-18T05:53:21.252766702Z"
        },
        {
          "author": "Jenny Valencia",
          "photo": "https://lh3.googleusercontent.com/a-/ALV-UjXrOJeLl9clbD55iHefDIrVJseiaw_0NOnW033KjaGkReTAWZ5M=s128-c0x00000000-cc-rp-mo",
          "rating": 5,
          "text": "It’s been 3 months since I had eyelid surgery at HERSHE, and I couldn't be happier with the results. From the start to finish, the entire experience was incredibly smooth and professional. The staff are warm, attentive, and made me feel comfortable every step of the way. The clinic itself is clean and beautifully designed, it really gave me a sense of trust as soon as I walked in.\n\nThe consultation was thorough, and the surgeon listened carefully to how I want my eyelid to be, while also giving expert advice. Post-surgery care has also been exceptional—they follow up diligently and genuinely care about my recovery and satisfaction.\n\nI'm truly a satisfied customer and so glad I chose Hershe for this procedure. Highly recommended to anyone considering eyelid surgery in South Korea!",
          "language": "en",
          "relative": "a year ago",
          "publishedAt": "2025-04-15T10:47:14.887670Z"
        },
        {
          "author": "Yiu Ha",
          "photo": "https://lh3.googleusercontent.com/a-/ALV-UjWmV2FCulsQeCnGLHS13BqFyBZtf-uAornzm6q5W809OdLlYURYOw=s128-c0x00000000-cc-rp-mo-ba3",
          "rating": 5,
          "text": "i had an incredible experience with hershe. specifically jessy was so sweet with me as my english interpretor. i finally got the results i was looking for in my revision eyelid and nose procedures! prices are reasonable, there is no upselling and i was very comfortable and felt taken care of the entire time from initial consultation to the procedures and transfers with their professional drivers! super classy touch. the surgeons were expert in their craft and judgment even though i know i had a lot to fix and they handled my case with care - i would trust them again! thanks to the nurse and jessy for holding my hand during the awake eyelid surgery!!",
          "language": "en",
          "relative": "2 months ago",
          "publishedAt": "2026-02-22T03:25:04.421577353Z"
        }
      ]
    },
    "source": "google"
  },
  "lienjang_강남점": {
    "fetchedAt": 1778551964019,
    "placeId": "ChIJ4S42bQejfDUR6YYyML0lxkE",
    "data": {
      "placeId": "ChIJ4S42bQejfDUR6YYyML0lxkE",
      "name": "Lienjang Plastic Surgery & Dermatology Gangnam Main Branch",
      "address": "403 Gangnam-daero, Seocho District, Seoul, South Korea",
      "rating": 4.6,
      "rating_count": 1443,
      "google_url": "https://maps.google.com/?cid=4739517152341690089&g_mp=CiVnb29nbGUubWFwcy5wbGFjZXMudjEuUGxhY2VzLkdldFBsYWNlEAIYBCAA",
      "website": "https://enlienjang.com/book-now/",
      "reviews": [
        {
          "author": "Bonbonnim",
          "photo": "https://lh3.googleusercontent.com/a-/ALV-UjV04TAyYFKB1jI-Wt2hj4_uDpKj13bY-3ykG7mO4A6mxS8vdISc=s128-c0x00000000-cc-rp-mo-ba3",
          "rating": 5,
          "text": "I had a wonderful experience at Lienjang Clinic. The consultation was very detailed and professional, and later during the treatment the doctor explained everything clearly about my skin condition, which made me feel comfortable and confident.\n\nThe doctors and staff were all very kind, attentive, and professional. I truly appreciated their careful approach and expertise.\n\nThe clinic itself is also very beautiful and luxurious, creating a pleasant and relaxing atmosphere. Overall, I am extremely satisfied with the service and would definitely recommend this clinic to others.",
          "language": "en",
          "relative": "2 months ago",
          "publishedAt": "2026-03-04T01:35:36.973671190Z"
        },
        {
          "author": "aysha alneyadi",
          "photo": "https://lh3.googleusercontent.com/a-/ALV-UjU3P0OOo7RY4INswNxXG2yw6Yie0vGYfUSkMVVzaIllAaOiDbrM=s128-c0x00000000-cc-rp-mo-ba4",
          "rating": 5,
          "text": "I recently had an aesthetic treatment at Lienjang in Seoul and could not be happier with my entire experience. As a non-Korean speaker, I was initially nervous about communication, but from the very first consultation, I felt completely at ease and understood.\n\nA huge thank you to Veronika Khan! Her ability to explain everything clearly in English was an absolute game-changer. She patiently answered all my questions, detailed the entire process, and made sure I was comfortable and informed every step of the way. She is a true asset to the clinic.\n\nFurthermore, the doctor and nurse were exceptional. They took the time to explain each step of the procedure in detail, showing genuine care and professionalism. They checked in on my comfort level throughout and made sure I knew exactly what to expect during and after the treatment.\n\nThe clinic itself is modern, clean, and has a calming atmosphere. The results are exactly what I hoped for—natural and refined.\n\nIf you are looking for a trustworthy, professional, and foreigner-friendly aesthetic center in Korea, look no further. My highest recommendation!",
          "language": "en",
          "relative": "4 months ago",
          "publishedAt": "2025-12-16T06:36:20.034122634Z"
        },
        {
          "author": "Gyury Yoon",
          "photo": "https://lh3.googleusercontent.com/a/ACg8ocIaoRq8NjgbM9-vTIFZop8LEPBvruK6dtyTr7ichPlAVRfFQw=s128-c0x00000000-cc-rp-mo",
          "rating": 5,
          "text": "From the moment I walked in, the staff made me feel comfortable and well taken care of. The clinic itself is beautifully designed—very neat with a soft, warm vibe. I was surprised that the waiting time was quite reasonable.\nThe doctor was both knowledgeable and gentle, and the entire team was genuinely friendly throughout my visit.",
          "language": "en",
          "relative": "2 months ago",
          "publishedAt": "2026-03-04T01:40:24.852821879Z"
        },
        {
          "author": "Aylin",
          "photo": "https://lh3.googleusercontent.com/a/ACg8ocKEQWqBhwADNaFjb2pY1YMVeZuIGhBgpeb6-xWW6NoG0yHhilGp=s128-c0x00000000-cc-rp-mo-ba4",
          "rating": 5,
          "text": "I’ve visited Lienjang together with my boyfriend last week and both of us had a few skincare treatments each.\n\nThe team was super professional, kind and highly knowledgeable and I felt in very safe hands.\n\nMy skin was slightly red right after the treatment but this only lasted 2h. I’m super happy with the results and my skin has been glowing since! Will definitely visit again on my next trip to Seoul 🇰🇷",
          "language": "en",
          "relative": "2 months ago",
          "publishedAt": "2026-02-26T11:43:49.338755468Z"
        },
        {
          "author": "완이로그",
          "photo": "https://lh3.googleusercontent.com/a-/ALV-UjWynI8lgcMvC4zJcvL8zNYjA3PM6enHaO8KzSdRWuLnforBnH8=s128-c0x00000000-cc-rp-mo",
          "rating": 5,
          "text": "It was a great experience overall.\nThe doctor was very professional and explained everything clearly, which made me feel confident and comfortable. The consultant was also very kind and helpful throughout the visit.\nThe clinic was clean and well-organized, giving a very hygienic and pleasant impression.\nI would definitely visit again.",
          "language": "en",
          "relative": "2 months ago",
          "publishedAt": "2026-03-04T01:54:41.530778791Z"
        }
      ]
    },
    "source": "google"
  },
  "dewyd_강남점": {
    "fetchedAt": 1778553573612,
    "placeId": "ChIJ7eJ8hdSjfDURcUeg1u5ajpE",
    "data": {
      "placeId": "ChIJ7eJ8hdSjfDURcUeg1u5ajpE",
      "name": "DewyD Clinic",
      "address": "South Korea, Seoul, Seocho District, 잠원동 Gangnam-daero, 621 K-TOWER 4층",
      "rating": 4.8,
      "rating_count": 293,
      "google_url": "https://maps.google.com/?cid=10488420564042008433&g_mp=CiVnb29nbGUubWFwcy5wbGFjZXMudjEuUGxhY2VzLkdldFBsYWNlEAIYBCAA",
      "website": "https://linktr.ee/dewydclinic",
      "reviews": [
        {
          "author": "Toni Cho",
          "photo": "https://lh3.googleusercontent.com/a/ACg8ocJf8iMuSK0rSc1f3zVL3d5I3_TXBtdvFA61qapgrqaQyquQlQ=s128-c0x00000000-cc-rp-mo-ba2",
          "rating": 5,
          "text": "It was my first visit, and the atmosphere was very comfortable and relaxing. The staff were extremely kind and welcoming.\nThey explained everything thoroughly before the procedure, so I felt at ease the whole time. I could notice the results right after the treatment and I’m very satisfied. I highly recommend Onda Lifting to anyone who’s considering it!",
          "language": "en",
          "relative": "3 months ago",
          "publishedAt": "2026-02-04T06:43:55.339178766Z"
        },
        {
          "author": "E. K.",
          "photo": "https://lh3.googleusercontent.com/a-/ALV-UjVSe9ryXhiCCcUQJnEiu72oSFqCDVtmQ0kZa1bhH6GG2a52LoE=s128-c0x00000000-cc-rp-mo-ba2",
          "rating": 5,
          "text": "DewyD Clinic is easily one of the most modern and stylish beauty clinics here in Seoul. The interior is very chic and the consultation rooms as well as the face washing station are very comfortable. It was also my first time meeting so many English speaking staff in a beauty clinic, which was such a nice surprise. An interpreter will accompany you every step of the process, so you can always ask questions or have a nice chat to calm your nerves before a treatment. 😉 I went in for a Onda + Titanium lifting treatment and saw the first effects immediately after. The location is also super convenient, right outside Sinsa station. ☺️",
          "language": "en",
          "relative": "4 months ago",
          "publishedAt": "2025-12-15T14:31:47.768030610Z"
        },
        {
          "author": "Maureen D’ Almeida",
          "photo": "https://lh3.googleusercontent.com/a/ACg8ocJjKo1oZXordoHw_p1MTbd_8D8KoBHiFlKaQyEKrmkxDAhu4w=s128-c0x00000000-cc-rp-mo",
          "rating": 5,
          "text": "I came to this clinic after seeing a video of a girl with the same skin tone as me and was encouraged to book an appointment. I am so glad I made the choice to come to Dewyd clinic. The staff are friendly, welcoming, attentive and knowledgeable. The clinic is foreigners friendly and the aesthetic is stunning. The consultation was informative and the treatments recommended aligned with my skin concerns. Although the extraction and injection treatments were painful, Capri laser and LDM were not. I can’t wait to see the results in a couple of days. 곰가랍니자!",
          "language": "en",
          "relative": "3 months ago",
          "publishedAt": "2026-01-21T02:20:59.052625855Z"
        },
        {
          "author": "-",
          "photo": "https://lh3.googleusercontent.com/a/ACg8ocLDtJH1Lksi_gRrWto-vKnOLnusR6JwWGy3GT45rl8OXMWnsw=s128-c0x00000000-cc-rp-mo-ba2",
          "rating": 5,
          "text": "​My experience at DewyD Clinic was incredibly clean and satisfying!\nFirst off, the staff members were exceptionally kind, and even the waiting area was so stylish, which immediately made me feel great.\nThe consultation was conducted with a professional interpreter, so I had no difficulty understanding anything. I was able to discuss my personal concerns, ask for the doctor's opinion, and determine the treatment plan that was right for me.\nIt’s true that the waiting time was a little long, but I figure that's just because it's such a popular clinic.\nOverall, I was extremely satisfied, and the results were fantastic! I definitely want to receive my next treatment here again!!",
          "language": "en",
          "relative": "6 months ago",
          "publishedAt": "2025-10-29T00:42:19.780978785Z"
        },
        {
          "author": "mathi turco",
          "photo": "https://lh3.googleusercontent.com/a-/ALV-UjVMZrOPst3_IM8wD31_WmXZQrpx3-Y4yqr4QxwTvf-l-FeyojkW=s128-c0x00000000-cc-rp-mo-ba2",
          "rating": 5,
          "text": "I had such a great experience at Dewyd Dermatology. I just did a hand rejuvenation treatment with Rejuran injections and Radiesse for a more plump, youthful look, and I’m honestly very satisfied with the results.\n\nThe treatment was painless, and the doctors were incredibly sweet, attentive, and reassuring throughout the entire process. The clinic itself is also super modern, spotless, and beautiful, which made the whole experience even better.\n\nHighly recommend if you’re looking for expert care in a comfortable, elegant setting.",
          "language": "en",
          "relative": "3 months ago",
          "publishedAt": "2026-02-05T15:08:50.689886833Z"
        }
      ]
    },
    "source": "google"
  },
  "soi_강남점": {
    "fetchedAt": 1778749148083,
    "placeId": "ChIJVVo2KxijfDURI9uIFSj3MRw",
    "data": {
      "placeId": "ChIJVVo2KxijfDURI9uIFSj3MRw",
      "name": "소이의원 | Soi Clinic",
      "address": "South Korea, Seoul, Seocho District, Jamwon-dong, 37-1 페이트플라자 7층",
      "rating": 5,
      "rating_count": 54,
      "google_url": "https://maps.google.com/?cid=2031676658452847395&g_mp=CiVnb29nbGUubWFwcy5wbGFjZXMudjEuUGxhY2VzLkdldFBsYWNlEAIYBCAA",
      "website": "https://www.soiclinic24.co.kr/",
      "reviews": [
        {
          "author": "Allison K",
          "photo": "https://lh3.googleusercontent.com/a/ACg8ocKIcQeIX4ek1YbRPGMy9YlwB8MwQAt-NYBhNyF7Z-AXiOcNNw=s128-c0x00000000-cc-rp-mo-ba2",
          "rating": 5,
          "text": "I had a wonderful experience at Soi Clinic as a foreigner. The staff were all incredibly kind and gentle. They always made sure I was not in any pain. The clinic is very clean and upscale.\n\nI got a hydrafacial and Botox. There was no downtime and my skin is so glowy. I will certainly be going back!",
          "language": "en",
          "relative": "6 months ago",
          "publishedAt": "2025-10-24T12:52:26.402617651Z"
        },
        {
          "author": "Silverline",
          "photo": "https://lh3.googleusercontent.com/a/ACg8ocLq9CZZqvk0sirS6xVc_MJ9N5ZofLQbVABQqo9R2IJve3wcRA=s128-c0x00000000-cc-rp-mo",
          "rating": 5,
          "text": "Thank you for the kind service! The doctor is really kind, she patiently explained all the detailed procedure one by one. Was so anxious, but after coming to the clinic feel much more assured! Also very nice space and facility 🥹 recommended, especially for foreigner like me. Sometimes getting beauty treatment in foreign country can be very daunting, but believe me it's worth it!!",
          "language": "en",
          "relative": "a year ago",
          "publishedAt": "2024-10-23T00:55:42.148133Z"
        }
      ],
      "review_lang_breakdown": {
        "en": 2
      }
    },
    "source": "google"
  },
  "ayun_청담점": {
    "fetchedAt": 1778599791440,
    "placeId": "ChIJ-0St6PShfDURcMa9eJ672FU",
    "data": {
      "placeId": "ChIJ-0St6PShfDURcMa9eJ672FU",
      "name": "아윤의원 강남 | AYUN Clinic Gangnam | 阿昀医美 | アユンクリニック",
      "address": "South Korea, Seoul, Seocho District, Gangnam-daero, 441 서산빌딩 7층",
      "rating": 5,
      "rating_count": 74,
      "google_url": "https://maps.google.com/?cid=6185900377498306160&g_mp=CiVnb29nbGUubWFwcy5wbGFjZXMudjEuUGxhY2VzLkdldFBsYWNlEAIYBCAA",
      "website": "https://ayunclinic.com/",
      "reviews": [
        {
          "author": "Diana Nafikova",
          "photo": "https://lh3.googleusercontent.com/a/ACg8ocJWvcJ4YVWypE2jX1QI4mOXUobo_HxhhCfD0idthklOijWJ3Q=s128-c0x00000000-cc-rp-mo",
          "rating": 5,
          "text": "I chose this clinic because it’s in a very convenient location, right near Gangnam Station. From the reception, all the staff were very friendly. The procedures were carried out professionally and without any delays. Everything went quickly and comfortably.",
          "language": "en",
          "relative": "in the last week",
          "publishedAt": "2026-05-12T07:40:04.654547060Z"
        },
        {
          "author": "Jane Sirata",
          "photo": "https://lh3.googleusercontent.com/a/ACg8ocLkaNjtEkH5SkZ39b15-b9p7L9Ylp8w_lLZA3f6rlGqIiok8A=s128-c0x00000000-cc-rp-mo-ba2",
          "rating": 5,
          "text": "I had a great experience at Ayun Clinic. The staff were all very friendly and made me feel comfortable from the moment I arrived. The doctor was especially caring took the time to understand my concerns and customized the treatment specifically for me. Really appreciate the personalized approach and attention to detail. Highly recommend!",
          "language": "en",
          "relative": "a week ago",
          "publishedAt": "2026-05-01T03:30:48.182954764Z"
        },
        {
          "author": "Chanakan O.",
          "photo": "https://lh3.googleusercontent.com/a-/ALV-UjU_0ZcP3IZeyivmhwfXAq_1kckCgmhq7GgedEiI1rsg8pQESzE=s128-c0x00000000-cc-rp-mo-ba3",
          "rating": 5,
          "text": "All the procedures are done fast. I came here for body’s fat injection all the process were done within 1 hour!",
          "language": "en",
          "relative": "a week ago",
          "publishedAt": "2026-05-01T02:33:14.072909048Z"
        },
        {
          "author": "Romina Aguilar",
          "photo": "https://lh3.googleusercontent.com/a-/ALV-UjXcVeCnQVmJrLU4kMRh-WXmLITnbqMZIlSDmURWaUP0XZAvH4iu=s128-c0x00000000-cc-rp-mo",
          "rating": 5,
          "text": "I'm leaving AYUN CLINIC extremely happy ~^^ The staff was very attentive and friendly, today was a wonderful beauty day, totally recommended!!!!",
          "language": "en",
          "relative": "a week ago",
          "publishedAt": "2026-04-30T08:34:06.830714427Z"
        },
        {
          "author": "Amy A",
          "photo": "https://lh3.googleusercontent.com/a/ACg8ocJ9O6Tuv6vjZFdyHUwssQFg7nBTr435Y2eXYtrOYa0MSIhG7w=s128-c0x00000000-cc-rp-mo",
          "rating": 5,
          "text": "I tried some skin boosters here..Kind and good",
          "language": "en",
          "relative": "2 months ago",
          "publishedAt": "2026-02-15T19:44:58.798444229Z"
        },
        {
          "author": "袁盼",
          "photo": "https://lh3.googleusercontent.com/a/ACg8ocKeEHjOiJ32GIJjtAvstJ2ZW6gHf7LYvad8AopKtD12L8pGMg=s128-c0x00000000-cc-rp-mo",
          "rating": 5,
          "text": "来打嘴巴玻尿酸，打之前还会敷麻药，没那么痛了，做完效果好满意！嘴巴嘟嘟的了！服务环境都很棒，还有中文翻译，很方便。",
          "language": "zh",
          "relative": "1周前",
          "publishedAt": "2026-04-29T09:01:58.653354984Z"
        },
        {
          "author": "欧阳红",
          "photo": "https://lh3.googleusercontent.com/a/ACg8ocLz0o3I9RVuomv1JZ_NCALe_-aTf6gXtcbNpmSHechykGPudg=s128-c0x00000000-cc-rp-mo",
          "rating": 5,
          "text": "来do嘴巴，环境非常好，一对一服务，疼痛管理也做的很好，英文交流顺畅。嘴巴打得超级好看！韩味很浓",
          "language": "zh",
          "relative": "1个月前",
          "publishedAt": "2026-04-01T02:53:40.530155086Z"
        },
        {
          "author": "黄雪婷",
          "photo": "https://lh3.googleusercontent.com/a/ACg8ocIFMVHcZJMqLQaF72LzzBx6IPDgAGdkvvdSUgCOa1u86NBmTA=s128-c0x00000000-cc-rp-mo",
          "rating": 5,
          "text": "环境很好下次还来",
          "language": "zh",
          "relative": "1个月前",
          "publishedAt": "2026-03-25T03:48:31.522282175Z"
        }
      ],
      "review_lang_breakdown": {
        "en": 5,
        "zh": 3
      }
    },
    "source": "google"
  }
}